flaccup/__init__.py
flaccup/cli.py
flaccup/core.py
flaccup/scheduler.py
flaccup/wizard.py
flaccup-1.0.0.dist-info/licenses/LICENSE
flaccup-1.0.0.dist-info/METADATA
flaccup-1.0.0.dist-info/WHEEL
flaccup-1.0.0.dist-info/entry_points.txt
flaccup-1.0.0.dist-info/top_level.txt
flaccup-1.0.0.dist-info/RECORD
