Metadata-Version: 2.4
Name: flaccup
Version: 1.0.0
Summary: FLAC Integrity Checker and Backup Utility
Home-page: https://github.com/BrendanStupik/flaccup
Author: Brendan Stupik
Author-email: flaccup@brendanstupik.anonaddy.com
Classifier: Development Status :: 4 - Beta
Classifier: Intended Audience :: End Users/Desktop
Classifier: Topic :: System :: Archiving :: Backup
Classifier: Topic :: Multimedia :: Sound/Audio :: Analysis
Classifier: Programming Language :: Python :: 3
Classifier: Programming Language :: Python :: 3.7
Classifier: Programming Language :: Python :: 3.8
Classifier: Programming Language :: Python :: 3.9
Classifier: Programming Language :: Python :: 3.10
Classifier: Programming Language :: Python :: 3.11
Classifier: Programming Language :: Python :: 3.12
Classifier: Operating System :: OS Independent
Requires-Python: >=3.7
License-File: LICENSE
Dynamic: author
Dynamic: author-email
Dynamic: classifier
Dynamic: description
Dynamic: description-content-type
Dynamic: home-page
Dynamic: license-file
Dynamic: requires-python
Dynamic: summary
